outliner/__init__.py
outliner/cli.py
outliner/display.py
outliner/outliner.py
outliner/trace.py
outliner_tracer-1.0.0.dist-info/LICENSE
outliner_tracer-1.0.0.dist-info/METADATA
outliner_tracer-1.0.0.dist-info/WHEEL
outliner_tracer-1.0.0.dist-info/entry_points.txt
outliner_tracer-1.0.0.dist-info/top_level.txt
outliner_tracer-1.0.0.dist-info/RECORD
