Metadata-Version: 2.1
Name: outliner-tracer
Version: 1.0.0
Summary: A tracer for compiled objects
Home-page: https://github.com/LucasAndradeDias/outliner
Author: Lucas A. Dias
Author-email: lucasan1234565@gmail.com
License: MIT
Keywords: tracer,outliner,tracing,complex,objects
License-File: LICENSE
